async_hyperliquid/__init__.py
async_hyperliquid/async_api.py
async_hyperliquid/async_hyperliquid.py
async_hyperliquid/exchange.py
async_hyperliquid/info.py
async_hyperliquid/utils/__init__.py
async_hyperliquid/utils/constants.py
async_hyperliquid/utils/decorators.py
async_hyperliquid/utils/miscs.py
async_hyperliquid/utils/signing.py
async_hyperliquid/utils/types.py
async_hyperliquid-0.3.4.dist-info/WHEEL
async_hyperliquid-0.3.4.dist-info/METADATA
async_hyperliquid-0.3.4.dist-info/RECORD
