Metadata-Version: 2.3
Name: async-hyperliquid
Version: 0.3.4
Summary: Async Hyperliquid client using aiohttp
Keywords: dex,hyperliquid,async,aiohttp,trading,cryptocurrency,defi
Author: Yuki
Author-email: Yuki <yuqi.lyle@gmail.com>
License: MIT License
Classifier: Development Status :: 4 - Beta
Classifier: Intended Audience :: Developers
Classifier: Intended Audience :: Financial and Insurance Industry
Classifier: License :: OSI Approved :: MIT License
Classifier: Operating System :: OS Independent
Classifier: Programming Language :: Python :: 3
Classifier: Programming Language :: Python :: 3.10
Classifier: Programming Language :: Python :: 3.11
Classifier: Programming Language :: Python :: 3.12
Classifier: Programming Language :: Python :: 3.13
Classifier: Programming Language :: Python :: 3 :: Only
Classifier: Topic :: Office/Business :: Financial :: Investment
Classifier: Topic :: Software Development :: Libraries :: Python Modules
Classifier: Topic :: Internet :: WWW/HTTP :: Dynamic Content
Classifier: Framework :: AsyncIO
Classifier: Framework :: aiohttp
Classifier: Typing :: Typed
Requires-Dist: aiohttp>=3.11.12,<4.0.0
Requires-Dist: msgpack>=1.1.0,<2.0.0
Requires-Dist: eth-account>=0.13.5,<0.14.0
Requires-Dist: eth-utils>=5.2.0,<6.0.0
Requires-Dist: hl-web3>=0.1.0
Requires-Python: >=3.10, <4
Project-URL: Changelog, https://github.com/traderfiapp/async-hyperliquid/blob/master/CHANGELOG.md
Project-URL: Documentation, https://github.com/traderfiapp/async-hyperliquid
Project-URL: Homepage, https://github.com/traderfiapp/async-hyperliquid
Project-URL: Issues, https://github.com/traderfiapp/async-hyperliquid/issues
Project-URL: Repository, https://github.com/traderfiapp/async-hyperliquid
